{
  "id" : "fruit",
  "name" : "Fruit",
  "background" : "background.webp",
  "cards" : [
    "cards/apple.webp",
    "cards/banana.webp",
    "cards/blueberry.webp",
    "cards/cherry.webp",
    "cards/coconut.webp",
    "cards/grapes.webp",
    "cards/lemon.webp",
    "cards/orange.webp",
    "cards/peach.webp",
    "cards/pear.webp",
    "cards/pineapple.webp",
    "cards/strawberry.webp",
    "cards/watermelon.webp"
  ],
  "icon" : "cards/apple.webp",
  "mascots" : [
    {
      "image" : "cards/apple.webp",
      "rotation" : 0,
      "y" : 721
    },
    {
      "image" : "cards/banana.webp",
      "rotation" : 0,
      "y" : 661
    },
    {
      "image" : "cards/strawberry.webp",
      "rotation" : 0,
      "y" : 680
    }
  ],
  "hash" : "9d8862d0bcb3ccff67d0e46f461c056bf69c840c6033f30c94871d504003de27"
}